{
  "stocks": [
    {
      "ticker": "MSFT",
      "name": "Microsoft Corporation",
      "price_native": 409.41,
      "prev_close": 408.0994,
      "currency": "USD",
      "change_pct": 0.32,
      "price_eur": 351.52,
      "prev_eur": 350.39,
      "sector": "Technology",
      "country": "United States",
      "pe_ratio": 25.636192,
      "beta": 1.108,
      "eps_ttm": 15.97,
      "dividend_yield": 0.89,
      "market_cap": 3042889957376,
      "recommendation": "buy",
      "analyst_total": 53,
      "analyst_target_mean": 510.54,
      "analyst_target_high": 626.78,
      "analyst_target_low": 336.57,
      "52w_high": 476.91,
      "52w_low": 296.04,
      "timestamp": "2026-03-10T11:17:57.020402",
      "shares": 5,
      "value_eur": 1757.6
    },
    {
      "ticker": "ENR.DE",
      "name": "Siemens Energy AG             N",
      "price_native": 156.75,
      "prev_close": 148.1,
      "currency": "EUR",
      "change_pct": 5.84,
      "price_eur": 156.75,
      "prev_eur": 148.1,
      "sector": "Industrials",
      "country": "Germany",
      "pe_ratio": 72.56944,
      "beta": 1.832,
      "eps_ttm": 2.16,
      "dividend_yield": 0.47,
      "market_cap": 134075203584,
      "recommendation": "buy",
      "analyst_total": 25,
      "analyst_target_mean": 165.68,
      "analyst_target_high": 220.0,
      "analyst_target_low": 89.0,
      "52w_high": 171.65,
      "52w_low": 41.81,
      "timestamp": "2026-03-10T11:17:57.322620",
      "shares": 9,
      "value_eur": 1410.75
    },
    {
      "ticker": "VH2.DE",
      "name": "Friedrich Vorwerk Group SE    I",
      "price_native": 82.6,
      "prev_close": 81.5,
      "currency": "EUR",
      "change_pct": 1.35,
      "price_eur": 82.6,
      "prev_eur": 81.5,
      "sector": "Industrials",
      "country": "Germany",
      "pe_ratio": 23.333334,
      "beta": 0.82,
      "eps_ttm": 3.54,
      "dividend_yield": 0.37,
      "market_cap": 1676610816,
      "recommendation": "hold",
      "analyst_total": 4,
      "analyst_target_mean": 88.5,
      "analyst_target_high": 111.0,
      "analyst_target_low": 65.0,
      "52w_high": 109.2,
      "52w_low": 38.75,
      "timestamp": "2026-03-10T11:17:57.621813",
      "shares": 11,
      "value_eur": 908.6
    },
    {
      "ticker": "MILDEF.ST",
      "name": "Mildef Group AB",
      "price_native": 130.6,
      "prev_close": 128.3,
      "currency": "SEK",
      "change_pct": 1.79,
      "price_eur": 12.25,
      "prev_eur": 12.03,
      "sector": "Industrials",
      "country": "Sweden",
      "pe_ratio": 41.329113,
      "beta": 1.167,
      "eps_ttm": 3.16,
      "dividend_yield": 0.58,
      "market_cap": 6150593536,
      "recommendation": "buy",
      "analyst_total": 5,
      "analyst_target_mean": 19.5,
      "analyst_target_high": 23.44,
      "analyst_target_low": 17.82,
      "52w_high": 27.61,
      "52w_low": 10.78,
      "timestamp": "2026-03-10T11:17:58.131567",
      "shares": 60,
      "value_eur": 735.0
    },
    {
      "ticker": "GOOG",
      "name": "Alphabet Inc.",
      "price_native": 306.01,
      "prev_close": 304.4617,
      "currency": "USD",
      "change_pct": 0.51,
      "price_eur": 262.74,
      "prev_eur": 261.41,
      "sector": "Communication Services",
      "country": "United States",
      "pe_ratio": 28.334259,
      "beta": 1.112,
      "eps_ttm": 10.8,
      "dividend_yield": 0.27,
      "market_cap": 3701803319296,
      "recommendation": "buy",
      "analyst_total": 17,
      "analyst_target_mean": 308.69,
      "analyst_target_high": 347.73,
      "analyst_target_low": 158.84,
      "52w_high": 300.64,
      "52w_low": 122.49,
      "timestamp": "2026-03-10T11:17:58.433906",
      "shares": 2,
      "value_eur": 525.48
    },
    {
      "ticker": "AIR.PA",
      "name": "AIRBUS SE",
      "price_native": 178.82,
      "prev_close": 175.64,
      "currency": "EUR",
      "change_pct": 1.81,
      "price_eur": 178.82,
      "prev_eur": 175.64,
      "sector": "Industrials",
      "country": "Netherlands",
      "pe_ratio": 27.09394,
      "beta": 0.835,
      "eps_ttm": 6.6,
      "dividend_yield": 1.82,
      "market_cap": 141139935232,
      "recommendation": "buy",
      "analyst_total": 22,
      "analyst_target_mean": 216.66,
      "analyst_target_high": 259.0,
      "analyst_target_low": 141.0,
      "52w_high": 221.3,
      "52w_low": 126.4,
      "timestamp": "2026-03-10T11:17:58.829590",
      "shares": 7,
      "value_eur": 1251.74
    },
    {
      "ticker": "HO.PA",
      "name": "THALES",
      "price_native": 251.5,
      "prev_close": 247.9,
      "currency": "EUR",
      "change_pct": 1.45,
      "price_eur": 251.5,
      "prev_eur": 247.9,
      "sector": "Industrials",
      "country": "France",
      "pe_ratio": 30.972906,
      "beta": 0.134,
      "eps_ttm": 8.12,
      "dividend_yield": 1.58,
      "market_cap": 51679391744,
      "recommendation": "buy",
      "analyst_total": 18,
      "analyst_target_mean": 292.67,
      "analyst_target_high": 380.0,
      "analyst_target_low": 240.0,
      "52w_high": 279.3,
      "52w_low": 207.0,
      "timestamp": "2026-03-10T11:17:59.209992",
      "shares": 5,
      "value_eur": 1257.5
    },
    {
      "ticker": "NVDA",
      "name": "NVIDIA Corporation",
      "price_native": 182.65,
      "prev_close": 181.36,
      "currency": "USD",
      "change_pct": 0.71,
      "price_eur": 156.82,
      "prev_eur": 155.72,
      "sector": "Technology",
      "country": "United States",
      "pe_ratio": 37.27551,
      "beta": 2.375,
      "eps_ttm": 4.9,
      "dividend_yield": 0.02,
      "market_cap": 4439307976704,
      "recommendation": "buy",
      "analyst_total": 56,
      "analyst_target_mean": 228.69,
      "analyst_target_high": 326.27,
      "analyst_target_low": 120.2,
      "52w_high": 182.19,
      "52w_low": 74.37,
      "timestamp": "2026-03-10T11:17:59.537144",
      "shares": 0,
      "value_eur": 0.0
    },
    {
      "ticker": "AMZN",
      "name": "Amazon.com, Inc.",
      "price_native": 213.49,
      "prev_close": 211.76,
      "currency": "USD",
      "change_pct": 0.82,
      "price_eur": 183.3,
      "prev_eur": 181.82,
      "sector": "Consumer Cyclical",
      "country": "United States",
      "pe_ratio": 29.775454,
      "beta": 1.42,
      "eps_ttm": 7.17,
      "dividend_yield": null,
      "market_cap": 2291798376448,
      "recommendation": "buy",
      "analyst_total": 62,
      "analyst_target_mean": 240.81,
      "analyst_target_high": 309.1,
      "analyst_target_low": 150.26,
      "52w_high": 222.03,
      "52w_low": 138.56,
      "timestamp": "2026-03-10T11:17:59.841344",
      "shares": 0,
      "value_eur": 0.0
    },
    {
      "ticker": "AAPL",
      "name": "Apple Inc.",
      "price_native": 259.88,
      "prev_close": 259.0,
      "currency": "USD",
      "change_pct": 0.34,
      "price_eur": 223.13,
      "prev_eur": 222.38,
      "sector": "Technology",
      "country": "United States",
      "pe_ratio": 32.896202,
      "beta": 1.116,
      "eps_ttm": 7.9,
      "dividend_yield": 0.4,
      "market_cap": 3819697078272,
      "recommendation": "buy",
      "analyst_total": 41,
      "analyst_target_mean": 253.66,
      "analyst_target_high": 300.51,
      "analyst_target_low": 176.01,
      "52w_high": 247.81,
      "52w_low": 145.28,
      "timestamp": "2026-03-10T11:18:00.218936",
      "shares": 0,
      "value_eur": 0.0
    },
    {
      "ticker": "LLY",
      "name": "Eli Lilly and Company",
      "price_native": 1008.39,
      "prev_close": 1002.7666,
      "currency": "USD",
      "change_pct": 0.56,
      "price_eur": 865.8,
      "prev_eur": 860.98,
      "sector": "Healthcare",
      "country": "United States",
      "pe_ratio": 43.862114,
      "beta": 0.434,
      "eps_ttm": 22.99,
      "dividend_yield": 0.62,
      "market_cap": 902527975424,
      "recommendation": "buy",
      "analyst_total": 29,
      "analyst_target_mean": 1042.64,
      "analyst_target_high": 1287.9,
      "analyst_target_low": 746.98,
      "52w_high": 973.61,
      "52w_low": 535.58,
      "timestamp": "2026-03-10T11:18:00.655506",
      "shares": 0,
      "value_eur": 0.0
    },
    {
      "ticker": "GBF.DE",
      "name": "Bilfinger SE                  I",
      "price_native": 107.3,
      "prev_close": 103.6,
      "currency": "EUR",
      "change_pct": 3.57,
      "price_eur": 107.3,
      "prev_eur": 103.6,
      "sector": "Industrials",
      "country": "Germany",
      "pe_ratio": 22.829788,
      "beta": 0.43,
      "eps_ttm": 4.7,
      "dividend_yield": 2.74,
      "market_cap": 3963632384,
      "recommendation": "buy",
      "analyst_total": 4,
      "analyst_target_mean": 122.5,
      "analyst_target_high": 132.0,
      "analyst_target_low": 109.0,
      "52w_high": 129.3,
      "52w_low": 54.25,
      "timestamp": "2026-03-10T11:18:01.095480",
      "shares": 0,
      "value_eur": 0.0
    },
    {
      "ticker": "BA.L",
      "name": "BAE SYSTEMS PLC ORD 2.5P",
      "price_native": 2252.0,
      "prev_close": 2268.0,
      "currency": "GBX",
      "change_pct": -0.71,
      "price_eur": 26.01,
      "prev_eur": 26.19,
      "sector": "Industrials",
      "country": "United Kingdom",
      "pe_ratio": 33.11765,
      "beta": 0.005,
      "eps_ttm": 0.68,
      "dividend_yield": 1.61,
      "market_cap": 65662107648,
      "recommendation": "buy",
      "analyst_total": 18,
      "analyst_target_mean": 26.43,
      "analyst_target_high": 30.02,
      "analyst_target_low": 19.63,
      "52w_high": 26.49,
      "52w_low": 16.1,
      "timestamp": "2026-03-10T11:18:01.668532",
      "shares": 0,
      "value_eur": 0.0
    },
    {
      "ticker": "BESI.AS",
      "name": "BE Semiconductor Industries N.V",
      "price_native": 170.65,
      "prev_close": 165.75,
      "currency": "EUR",
      "change_pct": 2.96,
      "price_eur": 170.65,
      "prev_eur": 165.75,
      "sector": "Technology",
      "country": "Netherlands",
      "pe_ratio": 102.8012,
      "beta": 1.223,
      "eps_ttm": 1.66,
      "dividend_yield": 0.95,
      "market_cap": 13445920768,
      "recommendation": "buy",
      "analyst_total": 23,
      "analyst_target_mean": 186.17,
      "analyst_target_high": 238.0,
      "analyst_target_low": 105.0,
      "52w_high": 198.8,
      "52w_low": 79.62,
      "timestamp": "2026-03-10T11:18:02.002366",
      "shares": 0,
      "value_eur": 0.0
    },
    {
      "ticker": "ASM.AS",
      "name": "ASM International N.V.",
      "price_native": 696.8,
      "prev_close": 671.4,
      "currency": "EUR",
      "change_pct": 3.78,
      "price_eur": 696.8,
      "prev_eur": 671.4,
      "sector": "Technology",
      "country": "Netherlands",
      "pe_ratio": 47.498295,
      "beta": 1.46,
      "eps_ttm": 14.67,
      "dividend_yield": 0.48,
      "market_cap": 34211485696,
      "recommendation": "buy",
      "analyst_total": 20,
      "analyst_target_mean": 793.75,
      "analyst_target_high": 950.0,
      "analyst_target_low": 600.0,
      "52w_high": 759.4,
      "52w_low": 333.3,
      "timestamp": "2026-03-10T11:18:02.346917",
      "shares": 0,
      "value_eur": 0.0
    }
  ],
  "etfs": [
    {
      "ticker": "SPYY.DE",
      "name": "SPDR MSCI ACW UCITS ETF       R",
      "price_native": 251.85,
      "prev_close": 248.85,
      "currency": "EUR",
      "change_pct": 1.21,
      "price_eur": 251.85,
      "prev_eur": 248.85,
      "sector": "",
      "country": "",
      "pe_ratio": null,
      "beta": null,
      "eps_ttm": null,
      "dividend_yield": null,
      "market_cap": null,
      "analyst_total": 0,
      "52w_high": 257.25,
      "52w_low": 182.56,
      "timestamp": "2026-03-10T11:18:02.623489",
      "shares": 47,
      "value_eur": 11836.95
    },
    {
      "ticker": "EUNK.DE",
      "name": "iShsIII-C.MSCI Eu.U.E.EUR Acc R",
      "price_native": 96.57,
      "prev_close": 94.65,
      "currency": "EUR",
      "change_pct": 2.03,
      "price_eur": 96.57,
      "prev_eur": 94.65,
      "sector": "",
      "country": "",
      "pe_ratio": 19.212276,
      "beta": null,
      "eps_ttm": null,
      "dividend_yield": null,
      "market_cap": null,
      "analyst_total": 0,
      "52w_high": 101.1,
      "52w_low": 72.15,
      "timestamp": "2026-03-10T11:18:02.893743",
      "shares": 83,
      "value_eur": 8015.31
    },
    {
      "ticker": "QDVE.DE",
      "name": "iShsV-S&P 500 Inf.Te.Sec.U.ETFR",
      "price_native": 34.48,
      "prev_close": 34.17,
      "currency": "EUR",
      "change_pct": 0.91,
      "price_eur": 34.48,
      "prev_eur": 34.17,
      "sector": "",
      "country": "",
      "pe_ratio": null,
      "beta": null,
      "eps_ttm": null,
      "dividend_yield": null,
      "market_cap": null,
      "analyst_total": 0,
      "52w_high": 38.54,
      "52w_low": 22.1,
      "timestamp": "2026-03-10T11:18:03.206449",
      "shares": 84,
      "value_eur": 2896.32
    },
    {
      "ticker": "IS3N.DE",
      "name": "iShs Core MSCI EM IMI U.ETF   R",
      "price_native": 41.366,
      "prev_close": 40.619,
      "currency": "EUR",
      "change_pct": 1.84,
      "price_eur": 41.37,
      "prev_eur": 40.62,
      "sector": "",
      "country": "",
      "pe_ratio": null,
      "beta": null,
      "eps_ttm": null,
      "dividend_yield": null,
      "market_cap": null,
      "analyst_total": 0,
      "52w_high": 44.18,
      "52w_low": 27.8,
      "timestamp": "2026-03-10T11:18:03.486113",
      "shares": 18,
      "value_eur": 744.66
    }
  ],
  "total_eur": 31339.91,
  "timestamp": "2026-03-10T11:17:56.369476"
}